leetcodepy/__init__.py
leetcodepy/easy.py
leetcodepy/hard.py
leetcodepy/medium.py
leetcodepy/utils.py
leetcodepy-0.0.2.dist-info/METADATA
leetcodepy-0.0.2.dist-info/WHEEL
leetcodepy-0.0.2.dist-info/licenses/LICENSE
leetcodepy-0.0.2.dist-info/RECORD
