Metadata-Version: 2.3
Name: leetcodepy
Version: 0.0.2
Summary: Implementations of LeetCode problem solutions in Python
Project-URL: Homepage, https://github.com/LeetCode-Packages/Python
Project-URL: Issues, https://github.com/LeetCode-Packages/Python/issues
Author-email: tarolling <benitojoens@gmail.com>
Classifier: License :: OSI Approved :: MIT License
Classifier: Operating System :: OS Independent
Classifier: Programming Language :: Python :: 3
Requires-Python: >=3.12
